requests_pro-1.0.0.dist-info/licenses/LICENSE
requestspro/__init__.py
requestspro/audit.py
requestspro/audit_for_django.py
requestspro/auth.py
requestspro/client.py
requestspro/sessions.py
requestspro/token.py
requestspro/utc.py
requests_pro-1.0.0.dist-info/METADATA
requests_pro-1.0.0.dist-info/WHEEL
requests_pro-1.0.0.dist-info/top_level.txt
requests_pro-1.0.0.dist-info/RECORD
