Metadata-Version: 2.4
Name: requests-pro
Version: 1.0.0
Summary: RequestsPro: The easy way to build professional-grade API clients.
Author-email: Henrique Bastos <henrique@bastos.net>
License-Expression: MIT
Project-URL: Homepage, https://github.com/henriquebastos/requests-pro
Project-URL: Documentation, https://github.com/henriquebastos/requests-pro
Project-URL: Repository, https://github.com/henriquebastos/requests-pro
Project-URL: Issue Tracker, https://github.com/henriquebastos/requests-pro/issues
Keywords: http,api,client,requests,rest,api-client,http-client
Classifier: Development Status :: 5 - Production/Stable
Classifier: Intended Audience :: Developers
Classifier: Programming Language :: Python :: 3
Classifier: Programming Language :: Python :: 3.10
Classifier: Programming Language :: Python :: 3.11
Classifier: Programming Language :: Python :: 3.12
Classifier: Programming Language :: Python :: 3.13
Classifier: Programming Language :: Python :: Implementation :: CPython
Classifier: Programming Language :: Python :: Implementation :: PyPy
Classifier: Operating System :: OS Independent
Classifier: Topic :: Software Development :: Libraries :: Python Modules
Requires-Python: >=3.10
License-File: LICENSE
Requires-Dist: requests>=2.32.3
Dynamic: license-file
